Metadata-Version: 1.0
Name: NetComp
Version: 0.2.3
Summary: Network Comparison
Home-page: https://github.com/peterewills/NetComp
Author: Peter Wills
Author-email: peter.e.wills@gmail.com
License: MIT
Platform: UNKNOWN
